autoreport/__init__.py
autoreport/_version.py
autoreport/config_validator.py
autoreport/error_handler.py
autoreport/exceptions.py
autoreport/generator.py
autoreport/log_config.py
autoreport/main.py
autoreport/resource_manager.py
autoreport/config/__init__.py
autoreport/config/company_info.py
autoreport/config/constants.py
autoreport/config/domain_config.py
autoreport/config/fonts.py
autoreport/config/styles.py
autoreport/core/__init__.py
autoreport/core/config_validator.py
autoreport/core/error_handler.py
autoreport/core/exceptions.py
autoreport/core/generator.py
autoreport/core/log_config.py
autoreport/core/resource_manager.py
autoreport/document/__init__.py
autoreport/document/images.py
autoreport/document/pages.py
autoreport/document/paragraphs.py
autoreport/document/styles.py
autoreport/document/tables.py
autoreport/domains/water_quality/map_configs.py
autoreport/processor/__init__.py
autoreport/processor/config.py
autoreport/processor/downloader.py
autoreport/processor/extractor.py
autoreport/processor/maps.py
autoreport/processor/data/README.md
autoreport/processor/data/__init__.py
autoreport/processor/data/analyzer.py
autoreport/processor/data/matcher.py
autoreport/processor/data/processor.py
autoreport/processor/data/save_history.py
autoreport/processor/data/standardizer.py
autoreport/processor/data/utils.py
autoreport/resources/__init__.py
autoreport/resources/images/airport.png
autoreport/resources/images/logo.png
autoreport/resources/images/uav.png
autoreport/resources/images/waterpicture.png
autoreport/utils/__init__.py
autoreport/utils/font.py
autoreport/utils/geo.py
autoreport/utils/io.py
autoreport/utils/kml.py
autoreport/utils/numerical.py
autoreport/utils/path.py
autoreport/utils/text.py
aerospot_autoreport-1.7.1.dist-info/METADATA
aerospot_autoreport-1.7.1.dist-info/WHEEL
aerospot_autoreport-1.7.1.dist-info/entry_points.txt
aerospot_autoreport-1.7.1.dist-info/top_level.txt
aerospot_autoreport-1.7.1.dist-info/RECORD
