Metadata-Version: 2.4
Name: aerospot-autoreport
Version: 1.7.1
Summary: AeroSpot自动化报告生成工具
Author-email: Zhou Yuanqi <zyq1034378361@gmail.com>
License: MIT
Project-URL: Homepage, https://github.com/1034378361/AutoReportV2
Project-URL: Documentation, https://autoreport-v2.readthedocs.io/
Project-URL: Repository, https://github.com/1034378361/AutoReportV2
Project-URL: Bug Tracker, https://github.com/1034378361/AutoReportV2/issues
Keywords: report,generator,docx,automation,remote sensing
Classifier: Development Status :: 4 - Beta
Classifier: Intended Audience :: Developers
Classifier: License :: OSI Approved :: MIT License
Classifier: Operating System :: OS Independent
Classifier: Programming Language :: Python :: 3
Classifier: Programming Language :: Python :: 3.10
Classifier: Programming Language :: Python :: 3.11
Classifier: Programming Language :: Python :: 3.12
Classifier: Topic :: Office/Business :: Office Suites
Classifier: Topic :: Scientific/Engineering :: GIS
Classifier: Topic :: Text Processing :: Markup
Requires-Python: >=3.10
Requires-Dist: python-docx>=0.8.11
Requires-Dist: pandas>=1.3.0
Requires-Dist: numpy>=1.21.0
Requires-Dist: pillow>=8.3.0
Requires-Dist: requests>=2.25.0
Requires-Dist: python-dotenv>=0.19.0
Requires-Dist: openpyxl>=3.0.0
Requires-Dist: matplotlib>=3.5.0
Requires-Dist: seaborn>=0.11.0
Requires-Dist: scikit-learn>=1.0.0
Requires-Dist: autowaterqualitymodeler>=4.5.1
Requires-Dist: chardet>=5.2.0
Requires-Dist: opencv-python>=4.11.0.86
Requires-Dist: aliyun-python-sdk-core>=2.16.0
Requires-Dist: aliyun-python-sdk-kms>=2.16.5
Requires-Dist: aspose-words>=25.4.0
Requires-Dist: colorama>=0.4.6
Requires-Dist: crcmod>=1.7
Requires-Dist: dotenv>=0.9.9
Requires-Dist: fpdf>=1.7.2
Requires-Dist: jmespath>=0.10.0
Requires-Dist: oss2>=2.19.1
Requires-Dist: plum-dispatch>=1.7.4
Requires-Dist: pycryptodome>=3.22.0
Requires-Dist: pyyaml>=6.0.0
Requires-Dist: setuptools>=80.9.0
Requires-Dist: setuptools-scm>=8.3.0
Requires-Dist: spire-doc>=13.0.0
Requires-Dist: pykrige>=1.7.0
Requires-Dist: tables>=3.8.0
Requires-Dist: pywin32>=305; sys_platform == "win32"
Provides-Extra: dev
Requires-Dist: pytest>=8.3.0; extra == "dev"
Requires-Dist: pytest-cov>=6.1.0; extra == "dev"
Requires-Dist: coverage>=7.8.0; extra == "dev"
Requires-Dist: black>=21.0.0; extra == "dev"
Requires-Dist: flake8>=3.9.0; extra == "dev"
Requires-Dist: mypy>=0.910; extra == "dev"
Requires-Dist: pre-commit>=2.15.0; extra == "dev"
Requires-Dist: iniconfig>=2.1.0; extra == "dev"
Requires-Dist: pluggy>=1.6.0; extra == "dev"
